Metadata-Version: 2.1
Name: recordtype
Version: 1.4
Summary: Similar to namedtuple, but instances are mutable.
Home-page: https://bitbucket.org/ericvsmith/recordtype
Author: Eric V. Smith
Author-email: eric@trueblade.com
License: Apache License Version 2.0
Platform: UNKNOWN
Classifier: Development Status :: 5 - Production/Stable
Classifier: Intended Audience :: Developers
Classifier: License :: OSI Approved :: Apache Software License
Classifier: Topic :: Software Development :: Libraries :: Python Modules
Classifier: Programming Language :: Python :: 2.6
Classifier: Programming Language :: Python :: 2.7
Classifier: Programming Language :: Python :: 3
License-File: LICENSE.txt
License-File: NOTICE
